CHANGELOG.md
README.md
setup.py
talepy/__init__.py
talepy/async_transactions.py
talepy/exceptions.py
talepy/functional.py
talepy/py.typed
talepy/retries.py
talepy/steps.py
talepy.egg-info/PKG-INFO
talepy.egg-info/SOURCES.txt
talepy.egg-info/dependency_links.txt
talepy.egg-info/top_level.txt