Metadata-Version: 2.1
Name: talepy
Version: 0.8.0
Summary: Distributed Transactions Helper
Home-page: https://github.com/meadsteve/talepy
Author: Steve Brazier
Author-email: meadsteve@gmail.com
License: UNKNOWN
Keywords: saga,distributed transaction
Platform: UNKNOWN
Classifier: Programming Language :: Python
Classifier: Programming Language :: Python :: 3
Classifier: Development Status :: 4 - Beta
